<?xml version="1.0" encoding="utf-8" ?>
<dwsync>
<file name="glyphicons-halflings-regular.eot" server="sabinemarie-schilling.de//httpdocs/" local="130771760320000000" remote="130839638400000000" Dst="2" />
<file name="glyphicons-halflings-regular.woff" server="sabinemarie-schilling.de//httpdocs/" local="130771760320000000" remote="130839638400000000" Dst="2" />
<file name="glyphicons-halflings-regular.woff2" server="sabinemarie-schilling.de//httpdocs/" local="130771760320000000" remote="130839638400000000" Dst="2" />
<file name="glyphicons-halflings-regular.ttf" server="sabinemarie-schilling.de//httpdocs/" local="130771760320000000" remote="130839638400000000" Dst="2" />
<file name="glyphicons-halflings-regular.eot" server="h2516709.stratoserver.net//httpdocs/" local="130771760320000000" remote="133354384200000000" Dst="2" />
<file name="glyphicons-halflings-regular.ttf" server="h2516709.stratoserver.net//httpdocs/" local="130771760320000000" remote="133354384200000000" Dst="2" />
<file name="glyphicons-halflings-regular.woff" server="h2516709.stratoserver.net//httpdocs/" local="130771760320000000" remote="133354384200000000" Dst="2" />
<file name="glyphicons-halflings-regular.woff2" server="h2516709.stratoserver.net//httpdocs/" local="130771760320000000" remote="133354384200000000" Dst="2" />
<file name="glyphicons-halflings-regular.svg" server="h2516709.stratoserver.net//httpdocs/" local="130771760320000000" remote="133354384800000000" Dst="2" />
<file name="glyphicons-halflings-regular.eot" server="h2516709.stratoserver.net//devdocs/" local="130771760320000000" remote="132190872600000000" Dst="1" />
<file name="glyphicons-halflings-regular.ttf" server="h2516709.stratoserver.net//devdocs/" local="130771760320000000" remote="132190872600000000" Dst="1" />
<file name="glyphicons-halflings-regular.svg" server="h2516709.stratoserver.net//devdocs/" local="130771760320000000" remote="130958670600000000" Dst="1" />
<file name="glyphicons-halflings-regular.woff" server="h2516709.stratoserver.net//devdocs/" local="130771760320000000" remote="132190872600000000" Dst="1" />
<file name="glyphicons-halflings-regular.woff2" server="h2516709.stratoserver.net//devdocs/" local="130771760320000000" remote="132190872600000000" Dst="1" />
</dwsync>